CHANGES.md
CONTRIBUTING.md
Dockerfile
LICENSE
MANIFEST.in
README.md
ROADMAP.md
SWARM.md
requirements-dev.txt
requirements.txt
setup.py
tox.ini
compose/__init__.py
compose/config.py
compose/const.py
compose/container.py
compose/legacy.py
compose/progress_stream.py
compose/project.py
compose/proxy.py
compose/service.py
compose/state.py
compose/utils.py
compose/cli/__init__.py
compose/cli/colors.py
compose/cli/command.py
compose/cli/docker_client.py
compose/cli/docopt_command.py
compose/cli/errors.py
compose/cli/formatter.py
compose/cli/log_printer.py
compose/cli/main.py
compose/cli/multiplexer.py
compose/cli/utils.py
compose/cli/verbose_proxy.py
compose_monkey.egg-info/PKG-INFO
compose_monkey.egg-info/SOURCES.txt
compose_monkey.egg-info/dependency_links.txt
compose_monkey.egg-info/entry_points.txt
compose_monkey.egg-info/requires.txt
compose_monkey.egg-info/top_level.txt
contrib/completion/bash/docker-compose
tests/__init__.py
tests/fixtures/UpperCaseDir/docker-compose.yml
tests/fixtures/build-ctx/Dockerfile
tests/fixtures/build-path/docker-compose.yml
tests/fixtures/commands-composefile/docker-compose.yml
tests/fixtures/dockerfile-with-volume/Dockerfile
tests/fixtures/dockerfile_with_entrypoint/Dockerfile
tests/fixtures/dockerfile_with_entrypoint/docker-compose.yml
tests/fixtures/env/one.env
tests/fixtures/env/resolve.env
tests/fixtures/env/two.env
tests/fixtures/env-file/docker-compose.yml
tests/fixtures/env-file/test.env
tests/fixtures/environment-composefile/docker-compose.yml
tests/fixtures/extends/circle-1.yml
tests/fixtures/extends/circle-2.yml
tests/fixtures/extends/common.yml
tests/fixtures/extends/docker-compose.yml
tests/fixtures/extends/nested-intermediate.yml
tests/fixtures/extends/nested.yml
tests/fixtures/extends/nonexistent-path-base.yml
tests/fixtures/extends/nonexistent-path-child.yml
tests/fixtures/links-composefile/docker-compose.yml
tests/fixtures/longer-filename-composefile/docker-compose.yaml
tests/fixtures/multiple-composefiles/compose2.yml
tests/fixtures/multiple-composefiles/docker-compose.yml
tests/fixtures/no-composefile/.gitignore
tests/fixtures/ports-composefile/docker-compose.yml
tests/fixtures/ports-composefile-scale/docker-compose.yml
