Metadata-Version: 1.0
Name: compose-monkey
Version: 0.1.2
Summary: Multi-container orchestration for Docker
Home-page: https://www.docker.com/
Author: Docker, Inc.
Author-email: UNKNOWN
License: Apache License 2.0
Platform: UNKNOWN
